popv/__init__.py
popv/_faiss_knn_classifier.py
popv/_settings.py
popv/_utils.py
popv/annotation.py
popv/preprocessing.py
popv/visualization.py
popv/algorithms/__init__.py
popv/algorithms/_base_algorithm.py
popv/algorithms/_bbknn.py
popv/algorithms/_celltypist.py
popv/algorithms/_harmony.py
popv/algorithms/_onclass.py
popv/algorithms/_rf.py
popv/algorithms/_scanorama.py
popv/algorithms/_scanvi.py
popv/algorithms/_scvi.py
popv/algorithms/_svm.py
popv/algorithms/_xgboost.py
popv/hub/__init__.py
popv/hub/_get_metrics.py
popv/hub/_metadata.py
popv/hub/_model.py
popv/hub/_template.py
popv/reproducibility/_accuracy.py
popv/reproducibility/_alluvial.py
popv-0.6.0.dist-info/METADATA
popv-0.6.0.dist-info/WHEEL
popv-0.6.0.dist-info/licenses/LICENSE
popv-0.6.0.dist-info/RECORD
